inoreader/__init__.py
inoreader/article.py
inoreader/client.py
inoreader/config.py
inoreader/consts.py
inoreader/exception.py
inoreader/filter.py
inoreader/main.py
inoreader/sim.py
inoreader/subscription.py
inoreader/utils.py
python_inoreader-0.7.1.dist-info/METADATA
python_inoreader-0.7.1.dist-info/WHEEL
python_inoreader-0.7.1.dist-info/entry_points.txt
python_inoreader-0.7.1.dist-info/top_level.txt
python_inoreader-0.7.1.dist-info/RECORD
