Metadata-Version: 2.1
Name: python-inoreader
Version: 0.7.1
Summary: Python wrapper of Inoreader API
Author-email: Linusp <linusp1024@gmail.com>
License: MIT
Project-URL: Homepage, https://github.com/Linusp/python-inoreader
Classifier: License :: OSI Approved :: MIT License
Classifier: Programming Language :: Python
Classifier: Programming Language :: Python :: 3
Requires-Python: >=3.6
Requires-Dist: lxml
Requires-Dist: requests
Requires-Dist: PyYAML
Requires-Dist: click
Requires-Dist: requests-oauthlib
Requires-Dist: flask
Requires-Dist: tabulate
